googleWordCloud/__init__.py
googleWordCloud/googleWordCloud.py
googleWordCloud/googleWordCloudFns.py
google_word_cloud_Chaz9578-0.0.13.dist-info/LICENSE
google_word_cloud_Chaz9578-0.0.13.dist-info/METADATA
google_word_cloud_Chaz9578-0.0.13.dist-info/WHEEL
google_word_cloud_Chaz9578-0.0.13.dist-info/top_level.txt
google_word_cloud_Chaz9578-0.0.13.dist-info/RECORD
